freexml/__init__.py
freexml/loading/__init__.py
freexml/saving/__init__.py
freexml-0.0.0.dist-info/LICENSE
freexml-0.0.0.dist-info/METADATA
freexml-0.0.0.dist-info/WHEEL
freexml-0.0.0.dist-info/top_level.txt
freexml-0.0.0.dist-info/RECORD
